{"actinopterygii":[0],"and":[0,1,3],"animalia":[0],"are":[0],"bathysolea":[0],"chordata":[0],"class":[0],"classification":[0],"currently":[0,1],"daniel":[0],"december":[0],"deepwater":[0],"desoutter":[0],"eds":[0],"family":[0],"four":[0],"froese":[0],"genus":[0],"icon":[0,1,2,3],"in":[0,1,2],"is":[0,1,2,3],"kingdom":[0],"lactea":[0],"lagarderae":[0],"oceans":[0],"ofbathysolea":[0],"order":[0],"pauly":[0],"phylum":[0],"pleuronectiformes":[0],"polli":[0],"profundicola":[0],"rainer":[0],"recognized":[0],"references":[0],"roule":[0],"scientific":[0],"sole":[0],"soleidae":[0],"species":[0],"stub":[0,1,2],"there":[0],"this":[0,1,2,3],"version":[0],"about":[1],"add":[1],"added":[1],"adding":[1],"africa":[1],"african":[1],"agent":[1],"also":[1],"any":[1],"article":[1,3],"articlehas":[1],"articlesnovember":[1],"as":[1,2],"at":[1],"back":[1],"be":[1],"because":[1],"been":[1],"between":[1],"born":[1,3],"buymore":[1],"by":[1],"can":[1],"cannot":[1],"caps":[1],"career":[1],"categories":[1],"cement":[1],"circle":[1],"contract":[1],"deal":[1],"defender":[1],"established":[1],"fc":[1],"find":[1],"finished":[1],"for":[1],"foreign":[1],"free":[1],"from":[1,2],"gilbert":[1],"he":[1],"height":[1],"help":[1],"his":[1],"httpwwwsoccerwikiorgplayerphppid":[1],"if":[1,3],"images":[1],"it":[1,3],"jersey":[1],"join":[1],"joined":[1],"jstor":[1],"july":[1],"kgs":[1],"league":[1],"letter":[1],"likely":[1],"listed":[1],"local":[1],"mapemba":[1],"merged":[1],"moroka":[1],"mtn":[1],"newspapers":[1],"no":[1],"not":[1,2],"notability":[1],"november":[1],"of":[1,2,3],"on":[1,2],"out":[1],"part":[1],"played":[1],"player":[1,3],"please":[1],"policy":[1],"premier":[1],"premiership":[1],"profile":[1],"renewed":[1],"right":[1],"season":[1],"second":[1],"signed":[1],"similar":[1],"so":[1],"soccer":[1],"sources":[1],"south":[1],"started":[1],"strikers":[1],"swallows":[1],"team":[1],"that":[1,2],"the":[1,2,3],"then":[1],"they":[1],"three":[1],"to":[1,3],"topic":[1],"united":[1],"wanted":[1],"was":[1],"weight":[1],"went":[1],"where":[1],"which":[1],"wiki":[1],"wikimedia":[1],"win":[1],"with":[1,3],"wsvg":[1],"year":[1],"zimbabwe":[1],"zimbabwean":[1],"alpha":[2],"area":[2],"based":[2],"cc":[2],"code":[2],"colorsvg":[2],"comments":[2],"coordinates":[2],"country":[2],"covered":[2],"data":[2],"database":[2],"dst":[2],"external":[2],"file":[2],"follows":[2],"iso":[2],"links":[2],"mountain":[2],"mp":[2],"mstmdt":[2],"offset":[2],"other":[2,3],"standards":[2],"templatetzcoordinates":[2],"time":[2],"timezoneconvertercom":[2],"travelmathcom":[2],"twikiorg":[2],"tz":[2],"tzcomments":[2],"tzcoord":[2],"utc":[2],"world":[2],"zone":[2],"zonetab":[2],"academy":[3],"american":[3],"an":[3],"andy":[3],"archaeologist":[3],"articles":[3],"associated":[3],"athlete":[3],"atmospheric":[3],"austrian":[3],"author":[3],"building":[3],"change":[3],"czech":[3],"directly":[3],"disambiguation":[3],"femininestrakov":[3],"football":[3],"footballer":[3],"frantiek":[3],"gbor":[3],"government":[3],"handball":[3],"hellmuth":[3],"here":[3],"high":[3],"historian":[3],"hockey":[3],"host":[3],"hungarian":[3],"ice":[3],"intended":[3],"internal":[3],"iva":[3],"jerry":[3],"josef":[3],"jump":[3],"led":[3],"link":[3],"lists":[3],"magpie":[3],"manager":[3],"martin":[3],"may":[3],"meaning":[3],"mike":[3],"novelist":[3],"page":[3],"pavol":[3],"people":[3],"petr":[3],"point":[3],"producer":[3],"refer":[3],"republic":[3],"scientist":[3],"slovak":[3],"straka":[3],"strakov":[3],"surname":[3],"television":[3],"titlestraka":[3],"toms":[3],"vclav":[3],"venezuelan":[3],"wish":[3],"you":[3]}